hackthebox/__init__.py
hackthebox/challenge.py
hackthebox/constants.py
hackthebox/content.py
hackthebox/endgame.py
hackthebox/errors.py
hackthebox/fortress.py
hackthebox/htb.py
hackthebox/leaderboard.py
hackthebox/machine.py
hackthebox/search.py
hackthebox/solve.py
hackthebox/team.py
hackthebox/user.py
hackthebox/utils.py
hackthebox/vpn.py
PyHackTheBox-0.5.6.post1.dist-info/METADATA
PyHackTheBox-0.5.6.post1.dist-info/WHEEL
PyHackTheBox-0.5.6.post1.dist-info/top_level.txt
PyHackTheBox-0.5.6.post1.dist-info/RECORD
