Metadata-Version: 2.1
Name: PyHackTheBox
Version: 0.5.6.post1
Summary: A wrapper for the Hack The Box API.
Home-page: https://github.com/clubby789/htb-api
Author: clubby789@github.com
Author-email: clubby789@gmail.com
License: UNKNOWN
Project-URL: Documentation, https://pyhackthebox.readthedocs.io/en/latest/
Platform: UNKNOWN
Classifier: Programming Language :: Python :: 3
Classifier: Programming Language :: Python :: 3.8
Classifier: License :: OSI Approved :: MIT License
Classifier: Operating System :: OS Independent
Requires-Python: >=3.8
Requires-Dist: requests (==2.27.1)
Requires-Dist: python-dateutil (==2.8.2)
